{
    "code_of_conduct_url": null,
    "contribution_guidelines_url": "https://github.com/mysql/mysql-connector-python/blob/trunk/CONTRIBUTING.md",
    "dependent_repos_count": 476,
    "dependents_count": 1042,
    "deprecation_reason": null,
    "description": "A self-contained Python driver for communicating with MySQL servers, using an API that is compliant with the Python Database API Specification v2.0 (PEP 249).",
    "homepage": "https://dev.mysql.com/doc/connector-python/en/",
    "keywords": [
        "mysql",
        "database",
        "db",
        "connector",
        "driver"
    ],
    "language": "Python",
    "latest_release_number": "9.3.0",
    "latest_release_published_at": "2025-04-15T11:21:33.000Z",
    "latest_stable_release_number": "9.3.0",
    "latest_stable_release_published_at": "2025-04-15T11:21:33.000Z",
    "license_normalized": true,
    "licenses": "GNU GPLv2 (with FOSS License Exception)",
    "name": "mysql-connector-python",
    "normalized_licenses": [
        "GPL-2.0-with-font-exception"
    ],
    "package_manager_url": "https://pypi.org/project/mysql-connector-python/",
    "repository_license": "Other",
    "platform": "Pypi",
    "repository_status": null,
    "repository_url": "https://github.com/mysql/mysql-connector-python",
    "security_policy_url": "https://github.com/mysql/mysql-connector-python/security/policy"
}