{
    "code_of_conduct_url": null,
    "contribution_guidelines_url": null,
    "dependent_repos_count": 15,
    "dependents_count": 30,
    "deprecation_reason": null,
    "description": "Logging utilities for SpaCy",
    "homepage": "https://github.com/explosion/spacy-loggers",
    "keywords": [
        "logging",
        "machine-learning",
        "natural-language-processing",
        "nlp",
        "python",
        "spacy"
    ],
    "language": "Python",
    "latest_release_number": "1.0.5",
    "latest_release_published_at": "2023-09-11T12:26:50.000Z",
    "latest_stable_release_number": "1.0.5",
    "latest_stable_release_published_at": "2023-09-11T12:26:50.000Z",
    "license_normalized": false,
    "licenses": "MIT",
    "name": "spacy-loggers",
    "normalized_licenses": [
        "MIT"
    ],
    "package_manager_url": "https://pypi.org/project/spacy-loggers/",
    "repository_license": "MIT",
    "platform": "Pypi",
    "repository_status": null,
    "repository_url": "https://github.com/explosion/spacy-loggers",
    "security_policy_url": null
}